MANIFEST.in
README.md
README.rst
setup.cfg
setup.py
douban/__init__.py
douban/__main__.py
douban/album.py
douban/celebrity.py
douban/movie.py
douban/people.py
douban_dl.egg-info/PKG-INFO
douban_dl.egg-info/SOURCES.txt
douban_dl.egg-info/dependency_links.txt
douban_dl.egg-info/entry_points.txt
douban_dl.egg-info/requires.txt
douban_dl.egg-info/top_level.txt
utils/__init__.py
utils/file_utils.py