Metadata-Version: 2.1
Name: douban-dl
Version: 0.0.5
Summary: douban downloader, include album, celebrity
Home-page: https://github.com/einverne/douban-dl
Author: einverne
Author-email: einverne@gmail.com
License: MIT
Keywords: douban downloader
Platform: UNKNOWN
